hahnpro_flow_sdk/rpc/__init__.py
hahnpro_flow_sdk/rpc/rpc_server.py
hahnpro_flow_sdk-0.1.13.dist-info/WHEEL
hahnpro_flow_sdk-0.1.13.dist-info/METADATA
hahnpro_flow_sdk-0.1.13.dist-info/RECORD
